drapo/__init__.py
drapo/__main__.py
drapo/clickfig.py
drapo/cursor.py
drapo/demo.py
drapo/interactive_object.py
drapo/line.py
drapo/rectangle.py
tests/test_drapo.py
drapo-1.2.3.dist-info/LICENSE
drapo-1.2.3.dist-info/METADATA
drapo-1.2.3.dist-info/WHEEL
drapo-1.2.3.dist-info/top_level.txt
drapo-1.2.3.dist-info/RECORD
