Metadata-Version: 2.2
Name: drapo
Version: 1.2.3
Summary: Interactive features (cursor, draggable lines & rectangles, graphical input, clik-to-make-axes active, etc.) for Matplotlib.
Author-email: Olivier Vincent <ovinc.py@gmail.com>
License: BSD 3-Clause License
Project-URL: Homepage, https://github.com/ovinc/drapo
Project-URL: Documentation, https://github.com/ovinc/drapo/README.md
Project-URL: Repository, https://github.com/ovinc/drapo.git
Keywords: interactive,matplotlib,draggable,cursor,line,rectangle,ginput
Classifier: Programming Language :: Python :: 3
Classifier: Operating System :: OS Independent
Classifier: License :: OSI Approved :: BSD License
Requires-Python: >=3.6
License-File: LICENSE
Requires-Dist: matplotlib
Requires-Dist: importlib-metadata
